{
  "chart": {
    "title": {
      "text": "Mean Response Time by Authority"
    },
    "tooltip": {
      "trigger": "axis",
      "valueFormatter": "{value} min"
    },
    "xAxis": {
      "type": "category",
      "data": [
        "Signer Set",
        "Delegated Body",
        "Governance"
      ]
    },
    "yAxis": {
      "type": "log",
      "name": "Minutes (Log)"
    },
    "series": [
      {
        "type": "bar",
        "data": [
          {
            "value": 387.2,
            "itemStyle": {
              "color": "#2563EB"
            }
          },
          {
            "value": 569.7,
            "itemStyle": {
              "color": "#16A34A"
            }
          },
          {
            "value": 372891.4,
            "itemStyle": {
              "color": "#7C3AED"
            }
          }
        ]
      }
    ]
  }
}